unormalize/__init__.py
unormalize-2020.7.17.dist-info/LICENSE
unormalize-2020.7.17.dist-info/METADATA
unormalize-2020.7.17.dist-info/WHEEL
unormalize-2020.7.17.dist-info/entry_points.txt
unormalize-2020.7.17.dist-info/top_level.txt
unormalize-2020.7.17.dist-info/RECORD
