Metadata-Version: 2.1
Name: unormalize
Version: 2020.7.17
Summary: Unicode normalization filters
Home-page: https://github.com/eddieantonio/unormalize
Author: Eddie Antonio Santos
Author-email: easantos@ualberta.ca
License: MIT
Download-URL: https://github.com/eddieantonio/unormalize
Platform: UNKNOWN
Classifier: Development Status :: 5 - Production/Stable
Classifier: Programming Language :: Python
Classifier: Programming Language :: Python :: 2
Classifier: Programming Language :: Python :: 2.7
Classifier: Programming Language :: Python :: 3
Classifier: Programming Language :: Python :: 3.5
Classifier: Programming Language :: Python :: 3.6
Classifier: Programming Language :: Python :: 3.7
Classifier: Programming Language :: Python :: 3.8
Classifier: Environment :: Console
Classifier: License :: OSI Approved :: MIT License
Classifier: Topic :: Text Processing
Classifier: Topic :: Utilities
